{"nodes": [{"id": "d_turabit_nlp_ps5_backend_seed_settings_js", "label": "seed-settings.js", "file_type": "code", "source_file": "D:\\turabit nlp\\ps5\\backend\\seed-settings.js", "source_location": "L1"}, {"id": "backend_seed_settings_seed", "label": "seed()", "file_type": "code", "source_file": "D:\\turabit nlp\\ps5\\backend\\seed-settings.js", "source_location": "L25"}], "edges": [{"source": "d_turabit_nlp_ps5_backend_seed_settings_js", "target": "backend_seed_settings_seed", "relation": "contains", "confidence": "EXTRACTED", "source_file": "D:\\turabit nlp\\ps5\\backend\\seed-settings.js", "source_location": "L25", "weight": 1.0}], "raw_calls": [{"caller_nid": "backend_seed_settings_seed", "callee": "log", "source_file": "D:\\turabit nlp\\ps5\\backend\\seed-settings.js", "source_location": "L26"}, {"caller_nid": "backend_seed_settings_seed", "callee": "upsert", "source_file": "D:\\turabit nlp\\ps5\\backend\\seed-settings.js", "source_location": "L28"}, {"caller_nid": "backend_seed_settings_seed", "callee": "log", "source_file": "D:\\turabit nlp\\ps5\\backend\\seed-settings.js", "source_location": "L33"}, {"caller_nid": "backend_seed_settings_seed", "callee": "log", "source_file": "D:\\turabit nlp\\ps5\\backend\\seed-settings.js", "source_location": "L35"}, {"caller_nid": "backend_seed_settings_seed", "callee": "$disconnect", "source_file": "D:\\turabit nlp\\ps5\\backend\\seed-settings.js", "source_location": "L36"}]}